.gitignore
.travis.yml
LICENSE
README.md
setup.py
dimodmock/__init__.py
dimodmock.egg-info/PKG-INFO
dimodmock.egg-info/SOURCES.txt
dimodmock.egg-info/dependency_links.txt
dimodmock.egg-info/requires.txt
dimodmock.egg-info/top_level.txt
tests/__init__.py
tests/test_sampler_mock.py
tests/test_structured.py