Metadata-Version: 2.1
Name: dimodmock
Version: 1.0.0
Summary: Utilities for mocking dimod Samplers
Home-page: UNKNOWN
Author: Konrad Jałowiecki
Author-email: dexter2206@gmail.com
License: UNKNOWN
Keywords: dimod mock testing
Platform: UNKNOWN
Classifier: Programming Language :: Python :: 3
Classifier: License :: OSI Approved :: MIT License
Classifier: Operating System :: OS Independent
Requires-Python: >=3.6
